[
  {"user": "@snipes_254"},
  {"user": "@Micheal_K10"},
  {"user": "@m_capty"},
  {"user": "@dreamer_the_guy"},
  {"user": "@Famim_01"},
  {"user": "@ndarsteve61"},
  {"user": "@Ajayiadedapo05"},
  {"user": "@oundo_gooner"},
  {"user": "@DanielMwic67030"},
  {"user": "@AyikiP"},
  {"user": "@MosesPhares"},
  {"user": "@UnitedEra6"},
  {"user": "@gatta9707_"},
  {"user": "@yanitted"},
  {"user": "@ja_ramogi"},
  {"user": "@GuenterK13"},
  {"user": "@KVistoh"},
  {"user": "@mekky_ayo"},
  {"user": "@Eliaskaneke"},
  {"user": "@blaqchoppa"},
  {"user": "@weiyswa"},
  {"user": "@Samuel47577643"},
  {"user": "@PriscillaMabaso"},
  {"user": "@burah___"},
  {"user": "@obdo8wdf"},
  {"user": "@grindelKadse"},
  {"user": "@Bellaa254"},
  {"user": "@Sophiia_s1"},
  {"user": "@Kelecypt0"},
  {"user": "@felo_ottroh"},
  {"user": "@PureRiseTv"},
  {"user": "@choosedusername"},
  {"user": "@MaustvanR28695"},
  {"user": "@soste1M"},
  {"user": "@sailopari232A"},
  {"user": "@rpmanish1"},
  {"user": "@OfObj52066"},
  {"user": "@21KAREL"},
  {"user": "@Embassy_of_Mars"},
  {"user": "@StevenWate91203"},
  {"user": "@RhonieNu"},
  {"user": "@Richpasman"},
  {"user": "@Tre_Krayne"},
  {"user": "@NasaipinCollins"},
  {"user": "@JasonMa90104406"},
  {"user": "@ARRESTED41"},
  {"user": "@EssaysInfo"},
  {"user": "@KussAdventures"},
  {"user": "@GauravD85675938"},
  {"user": "@GazanGaslighter"},
  {"user": "@Leipafelix"},
  {"user": "@MidmarkOnsongo"},
  {"user": "@The_good_boy86"},
  {"user": "@LeinLeinGoAway"},
  {"user": "@its_murife"},
  {"user": "@lemaron95"},
  {"user": "@Lattecummer"},
  {"user": "@SportyStacey7"},
  {"user": "@OladokunElisha"},
  {"user": "@_CFC_AY"},
  {"user": "@wrdonthestrit"},
  {"user": "@arap_mamet"},
  {"user": "@iamdcvector15"},
  {"user": "@Gooddlovee"},
  {"user": "@Mike4best"},
  {"user": "@iam____saleem"},
  {"user": "@johnpauldooga"},
  {"user": "@ng14156"},
  {"user": "@arounyoung"},
  {"user": "@Kaka_Mtaleigh"},
  {"user": "@DaniCaky02dc"},
  {"user": "@FAMKN_MENHUM"},
  {"user": "@Yassin_Jiwe"},
  {"user": "@keesom106"},
  {"user": "@Evi105538"},
  {"user": "@Olekete20"},
  {"user": "@RoyalPlaque"},
  {"user": "@mangaze_7"},
  {"user": "@vandee_p"},
  {"user": "@MZEE_02"},
  {"user": "@Brighter6N"},
  {"user": "@growthhabit_"},
  {"user": "@Thetalentedbobi"},
  {"user": "@RedDevilPlug"},
  {"user": "@4hmpff"},
  {"user": "@CollinsDukeman"},
  {"user": "@Abiola626"},
  {"user": "@Jayboi0247"},
  {"user": "@Monetizationtip"},
  {"user": "@kigogodiaries"},
  {"user": "@Donaldofweb3"},
  {"user": "@Symbolis"},
  {"user": "@UTD_Seth"},
  {"user": "@PChampionz"},
  {"user": "@Jescah0"}
]
